setup.py
goear_dl/__init__.py
goear_dl/cli.py
goear_dl/compat.py
goear_dl/core.py
goear_dl/entities.py
goear_dl/main.py
goear_dl/utils.py
goear_dl.egg-info/PKG-INFO
goear_dl.egg-info/SOURCES.txt
goear_dl.egg-info/dependency_links.txt
goear_dl.egg-info/entry_points.txt
goear_dl.egg-info/requires.txt
goear_dl.egg-info/top_level.txt