Metadata-Version: 1.1
Name: goear-dl
Version: 0.1.2
Summary: download songs from goear
Home-page: https://github.com/joanfont/goear-dl
Author: Joan Font
Author-email: joanfont@gmail.com
License: GPLv2
Download-URL: https://github.com/joanfont/goear-dl
Keywords: goear download music
Platform: UNKNOWN
Classifier: Programming Language :: Python
Classifier: Programming Language :: Python :: 2
Classifier: Programming Language :: Python :: 2.7
Classifier: Programming Language :: Python :: 3
Classifier: Programming Language :: Python :: 3.1
Classifier: Programming Language :: Python :: 3.2
Classifier: Programming Language :: Python :: 3.3
Classifier: Programming Language :: Python :: 3.4
Classifier: Programming Language :: Python :: 3.5
Classifier: Environment :: Console
Classifier: Topic :: Multimedia :: Sound/Audio
Classifier: License :: OSI Approved :: GNU General Public License v2 (GPLv2)
Classifier: Operating System :: MacOS :: MacOS X
Classifier: Operating System :: POSIX :: Linux
Classifier: Topic :: Terminals
Classifier: Topic :: System :: Shells
Classifier: Topic :: Utilities
